jb_toc/__init__.py
jb_toc/handlers.py
jb_toc/titles.py
jb_toc/tests/__init__.py
jb_toc/tests/conftest.py
jb_toc/tests/test_get_titles.py
jb_toc/tests/test_health.py
jb_toc/tests/fixtures/header1.ipynb
jb_toc/tests/fixtures/header1.md
jb_toc/tests/fixtures/header2.ipynb
jb_toc/tests/fixtures/header2.md
jb_toc-2.0.1.data/data/etc/jupyter/jupyter_server_config.d/jb_toc.json
jb_toc-2.0.1.dist-info/METADATA
jb_toc-2.0.1.dist-info/WHEEL
jb_toc-2.0.1.dist-info/entry_points.txt
jb_toc-2.0.1.dist-info/licenses/LICENSE
jb_toc-2.0.1.dist-info/RECORD
