Metadata-Version: 2.4
Name: jb-toc
Version: 2.0.1
Summary: Server extension providing /jbtoc/titles for jb-toc-frontend, if Jupyter Server is available.
Project-URL: Homepage, https://github.com/ASFOpenSARlab/jb-toc
Project-URL: Repository, https://github.com/ASFOpenSARlab/jb-toc
Project-URL: Issues, https://github.com/ASFOpenSARlab/jb-toc/issues
License: BSD 3-Clause License
License-File: LICENSE
Keywords: jupyter,jupyter_book,jupyterlab,toc
Classifier: Framework :: Jupyter
Classifier: Framework :: Jupyter :: JupyterLab
Classifier: Framework :: Jupyter :: JupyterLab :: 4
Classifier: Framework :: Jupyter :: JupyterLab :: Extensions
Classifier: Framework :: Jupyter :: JupyterLab :: Extensions :: Prebuilt
Classifier: License :: OSI Approved :: BSD License
Classifier: Programming Language :: Python
Classifier: Programming Language :: Python :: 3
Classifier: Programming Language :: Python :: 3.10
Classifier: Programming Language :: Python :: 3.11
Classifier: Programming Language :: Python :: 3.12
Classifier: Programming Language :: Python :: 3.13
Requires-Python: >=3.10
Requires-Dist: jb-toc-frontend==2.0.1
Requires-Dist: jupyter-server-globbing
Requires-Dist: jupyter-server>=2.0.0
Provides-Extra: test
Requires-Dist: coverage; extra == 'test'
Requires-Dist: pytest; extra == 'test'
Requires-Dist: pytest-asyncio; extra == 'test'
Requires-Dist: pytest-cov; extra == 'test'
Requires-Dist: pytest-jupyter[server]>=0.6.0; extra == 'test'
